{"nm":"Flow 8","ddd":0,"h":600,"w":800,"meta":{"g":"LottieFiles Figma v42"},"layers":[{"ty":4,"nm":"layer1 / path3812","sr":1,"st":0,"op":39,"ip":0,"hd":false,"ddd":0,"bm":0,"hasMask":false,"ao":0,"ks":{"a":{"a":1,"k":[{"o":{"x":0,"y":0},"i":{"x":1,"y":1},"s":[28.86,56.5],"t":0},{"o":{"x":0,"y":0},"i":{"x":1,"y":1},"s":[28.86,56.5],"t":6},{"o":{"x":0,"y":0},"i":{"x":1,"y":1},"s":[28.86,56.5],"t":7},{"o":{"x":0,"y":0},"i":{"x":1,"y":1},"s":[28.86,56.5],"t":13},{"o":{"x":0,"y":0},"i":{"x":1,"y":1},"s":[28.86,56.5],"t":19},{"o":{"x":0,"y":0},"i":{"x":1,"y":1},"s":[28.86,56.5],"t":25},{"o":{"x":0,"y":0},"i":{"x":1,"y":1},"s":[28.86,56.5],"t":26},{"o":{"x":0,"y":0},"i":{"x":1,"y":1},"s":[28.86,56.5],"t":32},{"s":[28.86,56.5],"t":38}]},"s":{"a":1,"k":[{"o":{"x":0,"y":0},"i":{"x":1,"y":1},"s":[100,100],"t":0},{"o":{"x":0,"y":0},"i":{"x":1,"y":1},"s":[100,100],"t":6},{"o":{"x":0,"y":0},"i":{"x":1,"y":1},"s":[100,100],"t":7},{"o":{"x":0,"y":0},"i":{"x":1,"y":1},"s":[100,100],"t":13},{"o":{"x":0,"y":0},"i":{"x":1,"y":1},"s":[100,100],"t":19},{"o":{"x":0,"y":0},"i":{"x":1,"y":1},"s":[100,100],"t":25},{"o":{"x":0,"y":0},"i":{"x":1,"y":1},"s":[100,100],"t":26},{"o":{"x":0,"y":0},"i":{"x":1,"y":1},"s":[100,100],"t":32},{"s":[100,100],"t":38}]},"sk":{"a":0,"k":0},"p":{"a":1,"k":[{"o":{"x":0,"y":0},"i":{"x":1,"y":1},"s":[406.75,300],"t":0},{"o":{"x":0,"y":0},"i":{"x":1,"y":1},"s":[406.75,300],"t":6},{"o":{"x":0,"y":0},"i":{"x":1,"y":1},"s":[406.75,300],"t":7},{"o":{"x":0,"y":0},"i":{"x":1,"y":1},"s":[406.75,300],"t":13},{"o":{"x":0,"y":0},"i":{"x":1,"y":1},"s":[406.75,300],"t":19},{"o":{"x":0,"y":0},"i":{"x":1,"y":1},"s":[406.75,300],"t":25},{"o":{"x":0,"y":0},"i":{"x":1,"y":1},"s":[406.75,300],"t":26},{"o":{"x":0,"y":0},"i":{"x":1,"y":1},"s":[406.75,300],"t":32},{"s":[406.75,300],"t":38}]},"r":{"a":1,"k":[{"o":{"x":0,"y":0},"i":{"x":1,"y":1},"s":[0],"t":0},{"o":{"x":0,"y":0},"i":{"x":1,"y":1},"s":[0],"t":6},{"o":{"x":0,"y":0},"i":{"x":1,"y":1},"s":[0],"t":7},{"o":{"x":0,"y":0},"i":{"x":1,"y":1},"s":[0],"t":13},{"o":{"x":0,"y":0},"i":{"x":1,"y":1},"s":[0],"t":19},{"o":{"x":0,"y":0},"i":{"x":1,"y":1},"s":[0],"t":25},{"o":{"x":0,"y":0},"i":{"x":1,"y":1},"s":[0],"t":26},{"o":{"x":0,"y":0},"i":{"x":1,"y":1},"s":[0],"t":32},{"s":[0],"t":38}]},"sa":{"a":0,"k":0},"o":{"a":1,"k":[{"o":{"x":0,"y":0},"i":{"x":1,"y":1},"s":[100],"t":0},{"o":{"x":0,"y":0},"i":{"x":1,"y":1},"s":[100],"t":6},{"o":{"x":0,"y":0},"i":{"x":1,"y":1},"s":[100],"t":7},{"o":{"x":0,"y":0},"i":{"x":1,"y":1},"s":[100],"t":13},{"o":{"x":0,"y":0},"i":{"x":1,"y":1},"s":[100],"t":19},{"o":{"x":0,"y":0},"i":{"x":1,"y":1},"s":[100],"t":25},{"o":{"x":0,"y":0},"i":{"x":1,"y":1},"s":[100],"t":26},{"o":{"x":0,"y":0},"i":{"x":1,"y":1},"s":[100],"t":32},{"s":[100],"t":38}]}},"shapes":[{"ty":"sh","bm":0,"hd":false,"nm":"","d":1,"ks":{"a":1,"k":[{"o":{"x":0,"y":0},"i":{"x":1,"y":1},"s":[{"c":true,"i":[[0,0],[0,0],[0,0],[0,0],[0,0],[0,0],[0,0],[0,0]],"o":[[0,0],[0,0],[0,0],[0,0],[0,0],[0,0],[0,0],[0,0]],"v":[[8.66,1.15],[39.45,0],[24.28,35.75],[57.73,35.75],[8.66,113],[27.9,55.35],[0,55.2],[8.66,1.15]]}],"t":0},{"o":{"x":0,"y":0},"i":{"x":1,"y":1},"s":[{"c":true,"i":[[0,0],[0,0],[0,0],[0,0],[0,0],[0,0],[0,0],[0,0]],"o":[[0,0],[0,0],[0,0],[0,0],[0,0],[0,0],[0,0],[0,0]],"v":[[8.66,1.15],[39.45,0],[24.28,35.75],[57.73,35.75],[8.66,113],[27.9,55.35],[0,55.2],[8.66,1.15]]}],"t":6},{"o":{"x":0,"y":0},"i":{"x":1,"y":1},"s":[{"c":true,"i":[[0,0],[0,0],[0,0],[0,0],[0,0],[0,0],[0,0],[0,0]],"o":[[0,0],[0,0],[0,0],[0,0],[0,0],[0,0],[0,0],[0,0]],"v":[[8.66,1.15],[39.45,0],[24.28,35.75],[57.73,35.75],[8.66,113],[27.9,55.35],[0,55.2],[8.66,1.15]]}],"t":7},{"o":{"x":0,"y":0},"i":{"x":1,"y":1},"s":[{"c":true,"i":[[0,0],[0,0],[0,0],[0,0],[0,0],[0,0],[0,0],[0,0]],"o":[[0,0],[0,0],[0,0],[0,0],[0,0],[0,0],[0,0],[0,0]],"v":[[8.66,1.15],[39.45,0],[24.28,35.75],[57.73,35.75],[8.66,113],[27.9,55.35],[0,55.2],[8.66,1.15]]}],"t":13},{"o":{"x":0,"y":0},"i":{"x":1,"y":1},"s":[{"c":true,"i":[[0,0],[0,0],[0,0],[0,0],[0,0],[0,0],[0,0],[0,0]],"o":[[0,0],[0,0],[0,0],[0,0],[0,0],[0,0],[0,0],[0,0]],"v":[[8.66,1.15],[39.45,0],[24.28,35.75],[57.73,35.75],[8.66,113],[27.9,55.35],[0,55.2],[8.66,1.15]]}],"t":19},{"o":{"x":0,"y":0},"i":{"x":1,"y":1},"s":[{"c":true,"i":[[0,0],[0,0],[0,0],[0,0],[0,0],[0,0],[0,0],[0,0]],"o":[[0,0],[0,0],[0,0],[0,0],[0,0],[0,0],[0,0],[0,0]],"v":[[8.66,1.15],[39.45,0],[24.28,35.75],[57.73,35.75],[8.66,113],[27.9,55.35],[0,55.2],[8.66,1.15]]}],"t":25},{"o":{"x":0,"y":0},"i":{"x":1,"y":1},"s":[{"c":true,"i":[[0,0],[0,0],[0,0],[0,0],[0,0],[0,0],[0,0],[0,0]],"o":[[0,0],[0,0],[0,0],[0,0],[0,0],[0,0],[0,0],[0,0]],"v":[[8.66,1.15],[39.45,0],[24.28,35.75],[57.73,35.75],[8.66,113],[27.9,55.35],[0,55.2],[8.66,1.15]]}],"t":26},{"o":{"x":0,"y":0},"i":{"x":1,"y":1},"s":[{"c":true,"i":[[0,0],[0,0],[0,0],[0,0],[0,0],[0,0],[0,0],[0,0]],"o":[[0,0],[0,0],[0,0],[0,0],[0,0],[0,0],[0,0],[0,0]],"v":[[8.66,1.15],[39.45,0],[24.28,35.75],[57.73,35.75],[8.66,113],[27.9,55.35],[0,55.2],[8.66,1.15]]}],"t":32},{"s":[{"c":true,"i":[[0,0],[0,0],[0,0],[0,0],[0,0],[0,0],[0,0],[0,0]],"o":[[0,0],[0,0],[0,0],[0,0],[0,0],[0,0],[0,0],[0,0]],"v":[[8.66,1.15],[39.45,0],[24.28,35.75],[57.73,35.75],[8.66,113],[27.9,55.35],[0,55.2],[8.66,1.15]]}],"t":38}]}},{"ty":"fl","bm":0,"hd":false,"nm":"","c":{"a":1,"k":[{"o":{"x":0,"y":0},"i":{"x":1,"y":1},"s":[1,1,1],"t":0},{"o":{"x":0,"y":0},"i":{"x":1,"y":1},"s":[1,1,1],"t":6},{"o":{"x":0,"y":0},"i":{"x":1,"y":1},"s":[1,1,1],"t":7},{"o":{"x":0,"y":0},"i":{"x":1,"y":1},"s":[1,1,1],"t":13},{"o":{"x":0,"y":0},"i":{"x":1,"y":1},"s":[1,1,1],"t":19},{"o":{"x":0,"y":0},"i":{"x":1,"y":1},"s":[1,1,1],"t":25},{"o":{"x":0,"y":0},"i":{"x":1,"y":1},"s":[1,1,1],"t":26},{"o":{"x":0,"y":0},"i":{"x":1,"y":1},"s":[1,1,1],"t":32},{"s":[1,1,1],"t":38}]},"r":1,"o":{"a":1,"k":[{"o":{"x":0,"y":0},"i":{"x":1,"y":1},"s":[100],"t":0},{"o":{"x":0,"y":0},"i":{"x":1,"y":1},"s":[100],"t":6},{"o":{"x":0,"y":0},"i":{"x":1,"y":1},"s":[100],"t":7},{"o":{"x":0,"y":0},"i":{"x":1,"y":1},"s":[100],"t":13},{"o":{"x":0,"y":0},"i":{"x":1,"y":1},"s":[100],"t":19},{"o":{"x":0,"y":0},"i":{"x":1,"y":1},"s":[100],"t":25},{"o":{"x":0,"y":0},"i":{"x":1,"y":1},"s":[100],"t":26},{"o":{"x":0,"y":0},"i":{"x":1,"y":1},"s":[100],"t":32},{"s":[100],"t":38}]}}],"ind":1},{"ty":4,"nm":"layer1 / g3742 / rect1626","sr":1,"st":0,"op":39,"ip":0,"hd":false,"ddd":0,"bm":0,"hasMask":false,"ao":0,"ks":{"a":{"a":1,"k":[{"o":{"x":0,"y":0},"i":{"x":1,"y":1},"s":[9.62,41.34],"t":0},{"o":{"x":0,"y":0},"i":{"x":1,"y":1},"s":[9.62,41.34],"t":6},{"o":{"x":0,"y":0},"i":{"x":1,"y":1},"s":[9.62,41.34],"t":7},{"o":{"x":0,"y":0},"i":{"x":1,"y":1},"s":[9.62,41.34],"t":13},{"o":{"x":0,"y":0},"i":{"x":1,"y":1},"s":[9.62,41.34],"t":19},{"o":{"x":0,"y":0},"i":{"x":1,"y":1},"s":[9.62,41.34],"t":25},{"o":{"x":0,"y":0},"i":{"x":1,"y":1},"s":[9.62,41.34],"t":26},{"o":{"x":0,"y":0},"i":{"x":1,"y":1},"s":[9.62,41.34],"t":32},{"s":[9.62,41.34],"t":38}]},"s":{"a":1,"k":[{"o":{"x":0,"y":0},"i":{"x":1,"y":1},"s":[100,100],"t":0},{"o":{"x":0,"y":0},"i":{"x":1,"y":1},"s":[100,100],"t":6},{"o":{"x":0,"y":0},"i":{"x":1,"y":1},"s":[100,100],"t":7},{"o":{"x":0,"y":0},"i":{"x":1,"y":1},"s":[100,100],"t":13},{"o":{"x":0,"y":0},"i":{"x":1,"y":1},"s":[100,100],"t":19},{"o":{"x":0,"y":0},"i":{"x":1,"y":1},"s":[100,100],"t":25},{"o":{"x":0,"y":0},"i":{"x":1,"y":1},"s":[100,100],"t":26},{"o":{"x":0,"y":0},"i":{"x":1,"y":1},"s":[100,100],"t":32},{"s":[100,100],"t":38}]},"sk":{"a":0,"k":0},"p":{"a":1,"k":[{"o":{"x":0,"y":0},"i":{"x":1,"y":1},"s":[637.85,300],"t":0},{"o":{"x":0,"y":0},"i":{"x":1,"y":1},"s":[637.85,300],"t":6},{"o":{"x":0,"y":0},"i":{"x":1,"y":1},"s":[637.85,300],"t":7},{"o":{"x":0,"y":0},"i":{"x":1,"y":1},"s":[637.85,300],"t":13},{"o":{"x":0,"y":0},"i":{"x":1,"y":1},"s":[637.85,300],"t":19},{"o":{"x":0,"y":0},"i":{"x":1,"y":1},"s":[637.85,300],"t":25},{"o":{"x":0,"y":0},"i":{"x":1,"y":1},"s":[637.85,300],"t":26},{"o":{"x":0,"y":0},"i":{"x":1,"y":1},"s":[637.85,300],"t":32},{"s":[637.85,300],"t":38}]},"r":{"a":1,"k":[{"o":{"x":0,"y":0},"i":{"x":1,"y":1},"s":[0],"t":0},{"o":{"x":0,"y":0},"i":{"x":1,"y":1},"s":[0],"t":6},{"o":{"x":0,"y":0},"i":{"x":1,"y":1},"s":[0],"t":7},{"o":{"x":0,"y":0},"i":{"x":1,"y":1},"s":[0],"t":13},{"o":{"x":0,"y":0},"i":{"x":1,"y":1},"s":[0],"t":19},{"o":{"x":0,"y":0},"i":{"x":1,"y":1},"s":[0],"t":25},{"o":{"x":0,"y":0},"i":{"x":1,"y":1},"s":[0],"t":26},{"o":{"x":0,"y":0},"i":{"x":1,"y":1},"s":[0],"t":32},{"s":[0],"t":38}]},"sa":{"a":0,"k":0},"o":{"a":1,"k":[{"o":{"x":0,"y":0},"i":{"x":1,"y":1},"s":[100],"t":0},{"o":{"x":0,"y":0},"i":{"x":1,"y":1},"s":[100],"t":6},{"o":{"x":0,"y":0},"i":{"x":1,"y":1},"s":[100],"t":7},{"o":{"x":0,"y":0},"i":{"x":1,"y":1},"s":[100],"t":13},{"o":{"x":0,"y":0},"i":{"x":1,"y":1},"s":[100],"t":19},{"o":{"x":0,"y":0},"i":{"x":1,"y":1},"s":[100],"t":25},{"o":{"x":0,"y":0},"i":{"x":1,"y":1},"s":[100],"t":26},{"o":{"x":0,"y":0},"i":{"x":1,"y":1},"s":[100],"t":32},{"s":[100],"t":38}]}},"shapes":[{"ty":"sh","bm":0,"hd":false,"nm":"","d":1,"ks":{"a":1,"k":[{"o":{"x":0,"y":0},"i":{"x":1,"y":1},"s":[{"c":true,"i":[[0,0],[0,0],[0,10.51],[0,0],[11.29,3.62]],"o":[[0,0],[11.29,-3.62],[0,0],[0,-10.51],[0,0]],"v":[[0,0],[0,82.69],[19.24,59.62],[19.24,23.07],[0,0]]}],"t":0},{"o":{"x":0,"y":0},"i":{"x":1,"y":1},"s":[{"c":true,"i":[[0,0],[0,0],[0,10.51],[0,0],[11.29,3.62]],"o":[[0,0],[11.29,-3.62],[0,0],[0,-10.51],[0,0]],"v":[[0,0],[0,82.69],[19.24,59.62],[19.24,23.07],[0,0]]}],"t":6},{"o":{"x":0,"y":0},"i":{"x":1,"y":1},"s":[{"c":true,"i":[[0,0],[0,0],[0,10.51],[0,0],[11.29,3.62]],"o":[[0,0],[11.29,-3.62],[0,0],[0,-10.51],[0,0]],"v":[[0,0],[0,82.69],[19.24,59.62],[19.24,23.07],[0,0]]}],"t":7},{"o":{"x":0,"y":0},"i":{"x":1,"y":1},"s":[{"c":true,"i":[[0,0],[0,0],[0,10.51],[0,0],[11.29,3.62]],"o":[[0,0],[11.29,-3.62],[0,0],[0,-10.51],[0,0]],"v":[[0,0],[0,82.69],[19.24,59.62],[19.24,23.07],[0,0]]}],"t":13},{"o":{"x":0,"y":0},"i":{"x":1,"y":1},"s":[{"c":true,"i":[[0,0],[0,0],[0,10.51],[0,0],[11.29,3.62]],"o":[[0,0],[11.29,-3.62],[0,0],[0,-10.51],[0,0]],"v":[[0,0],[0,82.69],[19.24,59.62],[19.24,23.07],[0,0]]}],"t":19},{"o":{"x":0,"y":0},"i":{"x":1,"y":1},"s":[{"c":true,"i":[[0,0],[0,0],[0,10.51],[0,0],[11.29,3.62]],"o":[[0,0],[11.29,-3.62],[0,0],[0,-10.51],[0,0]],"v":[[0,0],[0,82.69],[19.24,59.62],[19.24,23.07],[0,0]]}],"t":25},{"o":{"x":0,"y":0},"i":{"x":1,"y":1},"s":[{"c":true,"i":[[0,0],[0,0],[0,10.51],[0,0],[11.29,3.62]],"o":[[0,0],[11.29,-3.62],[0,0],[0,-10.51],[0,0]],"v":[[0,0],[0,82.69],[19.24,59.62],[19.24,23.07],[0,0]]}],"t":26},{"o":{"x":0,"y":0},"i":{"x":1,"y":1},"s":[{"c":true,"i":[[0,0],[0,0],[0,10.51],[0,0],[11.29,3.62]],"o":[[0,0],[11.29,-3.62],[0,0],[0,-10.51],[0,0]],"v":[[0,0],[0,82.69],[19.24,59.62],[19.24,23.07],[0,0]]}],"t":32},{"s":[{"c":true,"i":[[0,0],[0,0],[0,10.51],[0,0],[11.29,3.62]],"o":[[0,0],[11.29,-3.62],[0,0],[0,-10.51],[0,0]],"v":[[0,0],[0,82.69],[19.24,59.62],[19.24,23.07],[0,0]]}],"t":38}]}},{"ty":"fl","bm":0,"hd":false,"nm":"","c":{"a":1,"k":[{"o":{"x":0,"y":0},"i":{"x":1,"y":1},"s":[0.6,0.6,0.6],"t":0},{"o":{"x":0,"y":0},"i":{"x":1,"y":1},"s":[0.6,0.6,0.6],"t":6},{"o":{"x":0,"y":0},"i":{"x":1,"y":1},"s":[0.6,0.6,0.6],"t":7},{"o":{"x":0,"y":0},"i":{"x":1,"y":1},"s":[0.6,0.6,0.6],"t":13},{"o":{"x":0,"y":0},"i":{"x":1,"y":1},"s":[0.6,0.6,0.6],"t":19},{"o":{"x":0,"y":0},"i":{"x":1,"y":1},"s":[0.6,0.6,0.6],"t":25},{"o":{"x":0,"y":0},"i":{"x":1,"y":1},"s":[0.6,0.6,0.6],"t":26},{"o":{"x":0,"y":0},"i":{"x":1,"y":1},"s":[0.6,0.6,0.6],"t":32},{"s":[0.6,0.6,0.6],"t":38}]},"r":1,"o":{"a":1,"k":[{"o":{"x":0,"y":0},"i":{"x":1,"y":1},"s":[100],"t":0},{"o":{"x":0,"y":0},"i":{"x":1,"y":1},"s":[100],"t":6},{"o":{"x":0,"y":0},"i":{"x":1,"y":1},"s":[100],"t":7},{"o":{"x":0,"y":0},"i":{"x":1,"y":1},"s":[100],"t":13},{"o":{"x":0,"y":0},"i":{"x":1,"y":1},"s":[100],"t":19},{"o":{"x":0,"y":0},"i":{"x":1,"y":1},"s":[100],"t":25},{"o":{"x":0,"y":0},"i":{"x":1,"y":1},"s":[100],"t":26},{"o":{"x":0,"y":0},"i":{"x":1,"y":1},"s":[100],"t":32},{"s":[100],"t":38}]}}],"ind":2},{"ty":4,"nm":"layer1 / rect238-8-4-8-2","sr":1,"st":0,"op":14,"ip":0,"hd":false,"ddd":0,"bm":0,"hasMask":false,"ao":0,"ks":{"a":{"a":1,"k":[{"o":{"x":0,"y":0},"i":{"x":1,"y":1},"s":[47.24,94.49],"t":0},{"o":{"x":0,"y":0},"i":{"x":1,"y":1},"s":[47.24,94.49],"t":0.29999999329447746},{"o":{"x":0,"y":0},"i":{"x":1,"y":1},"s":[47.24,94.49],"t":6},{"o":{"x":0,"y":0},"i":{"x":1,"y":1},"s":[47.24,94.49],"t":7},{"s":[47.24,94.49],"t":12.900000158697367}]},"s":{"a":1,"k":[{"o":{"x":0,"y":0},"i":{"x":1,"y":1},"s":[100,100],"t":0},{"o":{"x":0,"y":0},"i":{"x":1,"y":1},"s":[100,100],"t":0.29999999329447746},{"o":{"x":0,"y":0},"i":{"x":1,"y":1},"s":[100,100],"t":6},{"o":{"x":0,"y":0},"i":{"x":1,"y":1},"s":[100,100],"t":7},{"s":[100,100],"t":12.900000158697367}]},"sk":{"a":0,"k":0},"p":{"a":1,"k":[{"o":{"x":0,"y":0},"i":{"x":1,"y":1},"s":[199.77,300],"t":0},{"o":{"x":0,"y":0},"i":{"x":1,"y":1},"s":[199.77,300],"t":0.29999999329447746},{"o":{"x":0,"y":0},"i":{"x":1,"y":1},"s":[199.77,300],"t":6},{"o":{"x":0,"y":0},"i":{"x":1,"y":1},"s":[199.77,300],"t":7},{"s":[199.77,300],"t":12.900000158697367}]},"r":{"a":1,"k":[{"o":{"x":0,"y":0},"i":{"x":1,"y":1},"s":[0],"t":0},{"o":{"x":0,"y":0},"i":{"x":1,"y":1},"s":[0],"t":0.29999999329447746},{"o":{"x":0,"y":0},"i":{"x":1,"y":1},"s":[0],"t":6},{"o":{"x":0,"y":0},"i":{"x":1,"y":1},"s":[0],"t":7},{"s":[0],"t":12.900000158697367}]},"sa":{"a":0,"k":0},"o":{"a":1,"k":[{"o":{"x":0,"y":0},"i":{"x":1,"y":1},"s":[0],"t":0},{"o":{"x":0,"y":0},"i":{"x":1,"y":1},"s":[0],"t":0.29999999329447746},{"o":{"x":0,"y":0},"i":{"x":1,"y":1},"s":[100],"t":6},{"o":{"x":0,"y":0},"i":{"x":1,"y":1},"s":[100],"t":7},{"s":[0],"t":12.900000158697367}]}},"shapes":[{"ty":"sh","bm":0,"hd":false,"nm":"","d":1,"ks":{"a":1,"k":[{"o":{"x":0,"y":0},"i":{"x":1,"y":1},"s":[{"c":true,"i":[[0,0],[0,0],[0,0],[0,0],[0,14.21],[0,0],[-14.21,0]],"o":[[0,0],[-0.11,33.72],[0,0],[-14.21,0],[0,0],[0,-14.21],[0,0]],"v":[[25.66,0],[94.49,0],[94.49,188.98],[25.66,188.98],[0,163.32],[0,25.66],[25.66,0]]}],"t":0},{"o":{"x":0,"y":0},"i":{"x":1,"y":1},"s":[{"c":true,"i":[[0,0],[0,0],[0,0],[0,0],[0,14.21],[0,0],[-14.21,0]],"o":[[0,0],[-0.11,33.72],[0,0],[-14.21,0],[0,0],[0,-14.21],[0,0]],"v":[[25.66,0],[94.49,0],[94.49,188.98],[25.66,188.98],[0,163.32],[0,25.66],[25.66,0]]}],"t":0.29999999329447746},{"o":{"x":0,"y":0},"i":{"x":1,"y":1},"s":[{"c":true,"i":[[0,0],[0,0],[0,0],[0,0],[0,14.21],[0,0],[-14.21,0]],"o":[[0,0],[-0.11,33.72],[0,0],[-14.21,0],[0,0],[0,-14.21],[0,0]],"v":[[25.66,0],[94.49,0],[94.49,188.98],[25.66,188.98],[0,163.32],[0,25.66],[25.66,0]]}],"t":6},{"o":{"x":0,"y":0},"i":{"x":1,"y":1},"s":[{"c":true,"i":[[0,0],[0,0],[0,0],[0,0],[0,14.21],[0,0],[-14.21,0]],"o":[[0,0],[-0.11,33.72],[0,0],[-14.21,0],[0,0],[0,-14.21],[0,0]],"v":[[25.66,0],[94.49,0],[94.49,188.98],[25.66,188.98],[0,163.32],[0,25.66],[25.66,0]]}],"t":7},{"s":[{"c":true,"i":[[0,0],[0,0],[0,0],[0,0],[0,14.21],[0,0],[-14.21,0]],"o":[[0,0],[-0.11,33.72],[0,0],[-14.21,0],[0,0],[0,-14.21],[0,0]],"v":[[25.66,0],[94.49,0],[94.49,188.98],[25.66,188.98],[0,163.32],[0,25.66],[25.66,0]]}],"t":12.900000158697367}]}},{"ty":"fl","bm":0,"hd":false,"nm":"","c":{"a":1,"k":[{"o":{"x":0,"y":0},"i":{"x":1,"y":1},"s":[0.3216,0.7726,0.3647],"t":0},{"o":{"x":0,"y":0},"i":{"x":1,"y":1},"s":[0.3216,0.7726,0.3647],"t":0.29999999329447746},{"o":{"x":0,"y":0},"i":{"x":1,"y":1},"s":[0.3216,0.7726,0.3647],"t":6},{"o":{"x":0,"y":0},"i":{"x":1,"y":1},"s":[0.3216,0.7726,0.3647],"t":7},{"s":[0.3216,0.7726,0.3647],"t":12.900000158697367}]},"r":1,"o":{"a":1,"k":[{"o":{"x":0,"y":0},"i":{"x":1,"y":1},"s":[100],"t":0},{"o":{"x":0,"y":0},"i":{"x":1,"y":1},"s":[100],"t":0.29999999329447746},{"o":{"x":0,"y":0},"i":{"x":1,"y":1},"s":[100],"t":6},{"o":{"x":0,"y":0},"i":{"x":1,"y":1},"s":[100],"t":7},{"s":[100],"t":12.900000158697367}]}}],"ind":3},{"ty":4,"nm":"layer1 / rect238-8-4-8","sr":1,"st":0,"op":20,"ip":0,"hd":false,"ddd":0,"bm":0,"hasMask":false,"ao":0,"ks":{"a":{"a":1,"k":[{"o":{"x":0,"y":0},"i":{"x":1,"y":1},"s":[95.24,94.49],"t":0},{"o":{"x":0,"y":0},"i":{"x":1,"y":1},"s":[95.24,94.49],"t":6.600000075995922},{"o":{"x":0,"y":0},"i":{"x":1,"y":1},"s":[95.24,94.49],"t":13},{"s":[95.24,94.49],"t":19.20000024139881}]},"s":{"a":1,"k":[{"o":{"x":0,"y":0},"i":{"x":1,"y":1},"s":[100,100],"t":0},{"o":{"x":0,"y":0},"i":{"x":1,"y":1},"s":[100,100],"t":6.600000075995922},{"o":{"x":0,"y":0},"i":{"x":1,"y":1},"s":[100,100],"t":13},{"s":[100,100],"t":19.20000024139881}]},"sk":{"a":0,"k":0},"p":{"a":1,"k":[{"o":{"x":0,"y":0},"i":{"x":1,"y":1},"s":[247.77,300],"t":0},{"o":{"x":0,"y":0},"i":{"x":1,"y":1},"s":[247.77,300],"t":6.600000075995922},{"o":{"x":0,"y":0},"i":{"x":1,"y":1},"s":[247.77,300],"t":13},{"s":[247.77,300],"t":19.20000024139881}]},"r":{"a":1,"k":[{"o":{"x":0,"y":0},"i":{"x":1,"y":1},"s":[0],"t":0},{"o":{"x":0,"y":0},"i":{"x":1,"y":1},"s":[0],"t":6.600000075995922},{"o":{"x":0,"y":0},"i":{"x":1,"y":1},"s":[0],"t":13},{"s":[0],"t":19.20000024139881}]},"sa":{"a":0,"k":0},"o":{"a":1,"k":[{"o":{"x":0,"y":0},"i":{"x":1,"y":1},"s":[0],"t":0},{"o":{"x":0,"y":0},"i":{"x":1,"y":1},"s":[0],"t":6.600000075995922},{"o":{"x":0,"y":0},"i":{"x":1,"y":1},"s":[100],"t":13},{"s":[0],"t":19.20000024139881}]}},"shapes":[{"ty":"sh","bm":0,"hd":false,"nm":"","d":1,"ks":{"a":1,"k":[{"o":{"x":0,"y":0},"i":{"x":1,"y":1},"s":[{"c":true,"i":[[0,0],[0,0],[0,0],[0,0],[0,14.21],[0,0],[-14.21,0]],"o":[[0,0],[-0.11,33.72],[0,0],[-14.21,0],[0,0],[0,-14.21],[0,0]],"v":[[25.66,0],[190.49,0],[190.49,188.98],[25.66,188.98],[0,163.32],[0,25.66],[25.66,0]]}],"t":0},{"o":{"x":0,"y":0},"i":{"x":1,"y":1},"s":[{"c":true,"i":[[0,0],[0,0],[0,0],[0,0],[0,14.21],[0,0],[-14.21,0]],"o":[[0,0],[-0.11,33.72],[0,0],[-14.21,0],[0,0],[0,-14.21],[0,0]],"v":[[25.66,0],[190.49,0],[190.49,188.98],[25.66,188.98],[0,163.32],[0,25.66],[25.66,0]]}],"t":6.600000075995922},{"o":{"x":0,"y":0},"i":{"x":1,"y":1},"s":[{"c":true,"i":[[0,0],[0,0],[0,0],[0,0],[0,14.21],[0,0],[-14.21,0]],"o":[[0,0],[-0.11,33.72],[0,0],[-14.21,0],[0,0],[0,-14.21],[0,0]],"v":[[25.66,0],[190.49,0],[190.49,188.98],[25.66,188.98],[0,163.32],[0,25.66],[25.66,0]]}],"t":13},{"s":[{"c":true,"i":[[0,0],[0,0],[0,0],[0,0],[0,14.21],[0,0],[-14.21,0]],"o":[[0,0],[-0.11,33.72],[0,0],[-14.21,0],[0,0],[0,-14.21],[0,0]],"v":[[25.66,0],[190.49,0],[190.49,188.98],[25.66,188.98],[0,163.32],[0,25.66],[25.66,0]]}],"t":19.20000024139881}]}},{"ty":"fl","bm":0,"hd":false,"nm":"","c":{"a":1,"k":[{"o":{"x":0,"y":0},"i":{"x":1,"y":1},"s":[0.3216,0.7726,0.3647],"t":0},{"o":{"x":0,"y":0},"i":{"x":1,"y":1},"s":[0.3216,0.7726,0.3647],"t":6.600000075995922},{"o":{"x":0,"y":0},"i":{"x":1,"y":1},"s":[0.3216,0.7726,0.3647],"t":13},{"s":[0.3216,0.7726,0.3647],"t":19.20000024139881}]},"r":1,"o":{"a":1,"k":[{"o":{"x":0,"y":0},"i":{"x":1,"y":1},"s":[100],"t":0},{"o":{"x":0,"y":0},"i":{"x":1,"y":1},"s":[100],"t":6.600000075995922},{"o":{"x":0,"y":0},"i":{"x":1,"y":1},"s":[100],"t":13},{"s":[100],"t":19.20000024139881}]}}],"ind":4},{"ty":4,"nm":"layer1 / rect238-8-4-1","sr":1,"st":0,"op":27,"ip":0,"hd":false,"ddd":0,"bm":0,"hasMask":false,"ao":0,"ks":{"a":{"a":1,"k":[{"o":{"x":0,"y":0},"i":{"x":1,"y":1},"s":[142.24,94.49],"t":0},{"o":{"x":0,"y":0},"i":{"x":1,"y":1},"s":[142.24,94.49],"t":12.900000158697367},{"o":{"x":0,"y":0},"i":{"x":1,"y":1},"s":[142.24,94.49],"t":19},{"s":[142.24,94.49],"t":25.500000324100256}]},"s":{"a":1,"k":[{"o":{"x":0,"y":0},"i":{"x":1,"y":1},"s":[100,100],"t":0},{"o":{"x":0,"y":0},"i":{"x":1,"y":1},"s":[100,100],"t":12.900000158697367},{"o":{"x":0,"y":0},"i":{"x":1,"y":1},"s":[100,100],"t":19},{"s":[100,100],"t":25.500000324100256}]},"sk":{"a":0,"k":0},"p":{"a":1,"k":[{"o":{"x":0,"y":0},"i":{"x":1,"y":1},"s":[294.77,300],"t":0},{"o":{"x":0,"y":0},"i":{"x":1,"y":1},"s":[294.77,300],"t":12.900000158697367},{"o":{"x":0,"y":0},"i":{"x":1,"y":1},"s":[294.77,300],"t":19},{"s":[294.77,300],"t":25.500000324100256}]},"r":{"a":1,"k":[{"o":{"x":0,"y":0},"i":{"x":1,"y":1},"s":[0],"t":0},{"o":{"x":0,"y":0},"i":{"x":1,"y":1},"s":[0],"t":12.900000158697367},{"o":{"x":0,"y":0},"i":{"x":1,"y":1},"s":[0],"t":19},{"s":[0],"t":25.500000324100256}]},"sa":{"a":0,"k":0},"o":{"a":1,"k":[{"o":{"x":0,"y":0},"i":{"x":1,"y":1},"s":[0],"t":0},{"o":{"x":0,"y":0},"i":{"x":1,"y":1},"s":[0],"t":12.900000158697367},{"o":{"x":0,"y":0},"i":{"x":1,"y":1},"s":[100],"t":19},{"s":[0],"t":25.500000324100256}]}},"shapes":[{"ty":"sh","bm":0,"hd":false,"nm":"","d":1,"ks":{"a":1,"k":[{"o":{"x":0,"y":0},"i":{"x":1,"y":1},"s":[{"c":true,"i":[[0,0],[0,0],[0,0],[0,0],[0,14.21],[0,0],[-14.21,0]],"o":[[0,0],[-0.11,33.72],[0,0],[-14.21,0],[0,0],[0,-14.21],[0,0]],"v":[[25.66,0],[284.49,0],[284.49,188.98],[25.66,188.98],[0,163.32],[0,25.66],[25.66,0]]}],"t":0},{"o":{"x":0,"y":0},"i":{"x":1,"y":1},"s":[{"c":true,"i":[[0,0],[0,0],[0,0],[0,0],[0,14.21],[0,0],[-14.21,0]],"o":[[0,0],[-0.11,33.72],[0,0],[-14.21,0],[0,0],[0,-14.21],[0,0]],"v":[[25.66,0],[284.49,0],[284.49,188.98],[25.66,188.98],[0,163.32],[0,25.66],[25.66,0]]}],"t":12.900000158697367},{"o":{"x":0,"y":0},"i":{"x":1,"y":1},"s":[{"c":true,"i":[[0,0],[0,0],[0,0],[0,0],[0,14.21],[0,0],[-14.21,0]],"o":[[0,0],[-0.11,33.72],[0,0],[-14.21,0],[0,0],[0,-14.21],[0,0]],"v":[[25.66,0],[284.49,0],[284.49,188.98],[25.66,188.98],[0,163.32],[0,25.66],[25.66,0]]}],"t":19},{"s":[{"c":true,"i":[[0,0],[0,0],[0,0],[0,0],[0,14.21],[0,0],[-14.21,0]],"o":[[0,0],[-0.11,33.72],[0,0],[-14.21,0],[0,0],[0,-14.21],[0,0]],"v":[[25.66,0],[284.49,0],[284.49,188.98],[25.66,188.98],[0,163.32],[0,25.66],[25.66,0]]}],"t":25.500000324100256}]}},{"ty":"fl","bm":0,"hd":false,"nm":"","c":{"a":1,"k":[{"o":{"x":0,"y":0},"i":{"x":1,"y":1},"s":[0.3216,0.7726,0.3647],"t":0},{"o":{"x":0,"y":0},"i":{"x":1,"y":1},"s":[0.3216,0.7726,0.3647],"t":12.900000158697367},{"o":{"x":0,"y":0},"i":{"x":1,"y":1},"s":[0.3216,0.7726,0.3647],"t":19},{"s":[0.3216,0.7726,0.3647],"t":25.500000324100256}]},"r":1,"o":{"a":1,"k":[{"o":{"x":0,"y":0},"i":{"x":1,"y":1},"s":[100],"t":0},{"o":{"x":0,"y":0},"i":{"x":1,"y":1},"s":[100],"t":12.900000158697367},{"o":{"x":0,"y":0},"i":{"x":1,"y":1},"s":[100],"t":19},{"s":[100],"t":25.500000324100256}]}}],"ind":5},{"ty":4,"nm":"layer1 / rect238-8-4","sr":1,"st":0,"op":33,"ip":0,"hd":false,"ddd":0,"bm":0,"hasMask":false,"ao":0,"ks":{"a":{"a":1,"k":[{"o":{"x":0,"y":0},"i":{"x":1,"y":1},"s":[189.24,94.49],"t":0},{"o":{"x":0,"y":0},"i":{"x":1,"y":1},"s":[189.24,94.49],"t":19.20000024139881},{"o":{"x":0,"y":0},"i":{"x":1,"y":1},"s":[189.24,94.49],"t":25},{"o":{"x":0,"y":0},"i":{"x":1,"y":1},"s":[189.24,94.49],"t":26},{"s":[189.24,94.49],"t":31.8000004068017}]},"s":{"a":1,"k":[{"o":{"x":0,"y":0},"i":{"x":1,"y":1},"s":[100,100],"t":0},{"o":{"x":0,"y":0},"i":{"x":1,"y":1},"s":[100,100],"t":19.20000024139881},{"o":{"x":0,"y":0},"i":{"x":1,"y":1},"s":[100,100],"t":25},{"o":{"x":0,"y":0},"i":{"x":1,"y":1},"s":[100,100],"t":26},{"s":[100,100],"t":31.8000004068017}]},"sk":{"a":0,"k":0},"p":{"a":1,"k":[{"o":{"x":0,"y":0},"i":{"x":1,"y":1},"s":[341.77,300],"t":0},{"o":{"x":0,"y":0},"i":{"x":1,"y":1},"s":[341.77,300],"t":19.20000024139881},{"o":{"x":0,"y":0},"i":{"x":1,"y":1},"s":[341.77,300],"t":25},{"o":{"x":0,"y":0},"i":{"x":1,"y":1},"s":[341.77,300],"t":26},{"s":[341.77,300],"t":31.8000004068017}]},"r":{"a":1,"k":[{"o":{"x":0,"y":0},"i":{"x":1,"y":1},"s":[0],"t":0},{"o":{"x":0,"y":0},"i":{"x":1,"y":1},"s":[0],"t":19.20000024139881},{"o":{"x":0,"y":0},"i":{"x":1,"y":1},"s":[0],"t":25},{"o":{"x":0,"y":0},"i":{"x":1,"y":1},"s":[0],"t":26},{"s":[0],"t":31.8000004068017}]},"sa":{"a":0,"k":0},"o":{"a":1,"k":[{"o":{"x":0,"y":0},"i":{"x":1,"y":1},"s":[0],"t":0},{"o":{"x":0,"y":0},"i":{"x":1,"y":1},"s":[0],"t":19.20000024139881},{"o":{"x":0,"y":0},"i":{"x":1,"y":1},"s":[100],"t":25},{"o":{"x":0,"y":0},"i":{"x":1,"y":1},"s":[100],"t":26},{"s":[0],"t":31.8000004068017}]}},"shapes":[{"ty":"sh","bm":0,"hd":false,"nm":"","d":1,"ks":{"a":1,"k":[{"o":{"x":0,"y":0},"i":{"x":1,"y":1},"s":[{"c":true,"i":[[0,0],[0,0],[0,0],[0,0],[0,14.21],[0,0],[-14.21,0]],"o":[[0,0],[-0.11,33.72],[0,0],[-14.21,0],[0,0],[0,-14.21],[0,0]],"v":[[25.66,0],[378.49,0],[378.49,188.98],[25.66,188.98],[0,163.32],[0,25.66],[25.66,0]]}],"t":0},{"o":{"x":0,"y":0},"i":{"x":1,"y":1},"s":[{"c":true,"i":[[0,0],[0,0],[0,0],[0,0],[0,14.21],[0,0],[-14.21,0]],"o":[[0,0],[-0.11,33.72],[0,0],[-14.21,0],[0,0],[0,-14.21],[0,0]],"v":[[25.66,0],[378.49,0],[378.49,188.98],[25.66,188.98],[0,163.32],[0,25.66],[25.66,0]]}],"t":19.20000024139881},{"o":{"x":0,"y":0},"i":{"x":1,"y":1},"s":[{"c":true,"i":[[0,0],[0,0],[0,0],[0,0],[0,14.21],[0,0],[-14.21,0]],"o":[[0,0],[-0.11,33.72],[0,0],[-14.21,0],[0,0],[0,-14.21],[0,0]],"v":[[25.66,0],[378.49,0],[378.49,188.98],[25.66,188.98],[0,163.32],[0,25.66],[25.66,0]]}],"t":25},{"o":{"x":0,"y":0},"i":{"x":1,"y":1},"s":[{"c":true,"i":[[0,0],[0,0],[0,0],[0,0],[0,14.21],[0,0],[-14.21,0]],"o":[[0,0],[-0.11,33.72],[0,0],[-14.21,0],[0,0],[0,-14.21],[0,0]],"v":[[25.66,0],[378.49,0],[378.49,188.98],[25.66,188.98],[0,163.32],[0,25.66],[25.66,0]]}],"t":26},{"s":[{"c":true,"i":[[0,0],[0,0],[0,0],[0,0],[0,14.21],[0,0],[-14.21,0]],"o":[[0,0],[-0.11,33.72],[0,0],[-14.21,0],[0,0],[0,-14.21],[0,0]],"v":[[25.66,0],[378.49,0],[378.49,188.98],[25.66,188.98],[0,163.32],[0,25.66],[25.66,0]]}],"t":31.8000004068017}]}},{"ty":"fl","bm":0,"hd":false,"nm":"","c":{"a":1,"k":[{"o":{"x":0,"y":0},"i":{"x":1,"y":1},"s":[0.3216,0.7726,0.3647],"t":0},{"o":{"x":0,"y":0},"i":{"x":1,"y":1},"s":[0.3216,0.7726,0.3647],"t":19.20000024139881},{"o":{"x":0,"y":0},"i":{"x":1,"y":1},"s":[0.3216,0.7726,0.3647],"t":25},{"o":{"x":0,"y":0},"i":{"x":1,"y":1},"s":[0.3216,0.7726,0.3647],"t":26},{"s":[0.3216,0.7726,0.3647],"t":31.8000004068017}]},"r":1,"o":{"a":1,"k":[{"o":{"x":0,"y":0},"i":{"x":1,"y":1},"s":[100],"t":0},{"o":{"x":0,"y":0},"i":{"x":1,"y":1},"s":[100],"t":19.20000024139881},{"o":{"x":0,"y":0},"i":{"x":1,"y":1},"s":[100],"t":25},{"o":{"x":0,"y":0},"i":{"x":1,"y":1},"s":[100],"t":26},{"s":[100],"t":31.8000004068017}]}}],"ind":6},{"ty":4,"nm":"layer1 / rect238-87","sr":1,"st":0,"op":39,"ip":0,"hd":false,"ddd":0,"bm":0,"hasMask":false,"ao":0,"ks":{"a":{"a":1,"k":[{"o":{"x":0,"y":0},"i":{"x":1,"y":1},"s":[236.22,94.49],"t":0},{"o":{"x":0,"y":0},"i":{"x":1,"y":1},"s":[236.22,94.49],"t":25.500000324100256},{"o":{"x":0,"y":0},"i":{"x":1,"y":1},"s":[236.22,94.49],"t":32},{"s":[236.22,94.49],"t":38.100000489503145}]},"s":{"a":1,"k":[{"o":{"x":0,"y":0},"i":{"x":1,"y":1},"s":[100,100],"t":0},{"o":{"x":0,"y":0},"i":{"x":1,"y":1},"s":[100,100],"t":25.500000324100256},{"o":{"x":0,"y":0},"i":{"x":1,"y":1},"s":[100,100],"t":32},{"s":[100,100],"t":38.100000489503145}]},"sk":{"a":0,"k":0},"p":{"a":1,"k":[{"o":{"x":0,"y":0},"i":{"x":1,"y":1},"s":[388.75,300],"t":0},{"o":{"x":0,"y":0},"i":{"x":1,"y":1},"s":[388.75,300],"t":25.500000324100256},{"o":{"x":0,"y":0},"i":{"x":1,"y":1},"s":[388.75,300],"t":32},{"s":[388.75,300],"t":38.100000489503145}]},"r":{"a":1,"k":[{"o":{"x":0,"y":0},"i":{"x":1,"y":1},"s":[0],"t":0},{"o":{"x":0,"y":0},"i":{"x":1,"y":1},"s":[0],"t":25.500000324100256},{"o":{"x":0,"y":0},"i":{"x":1,"y":1},"s":[0],"t":32},{"s":[0],"t":38.100000489503145}]},"sa":{"a":0,"k":0},"o":{"a":1,"k":[{"o":{"x":0,"y":0},"i":{"x":1,"y":1},"s":[0],"t":0},{"o":{"x":0,"y":0},"i":{"x":1,"y":1},"s":[0],"t":25.500000324100256},{"o":{"x":0,"y":0},"i":{"x":1,"y":1},"s":[100],"t":32},{"s":[0],"t":38.100000489503145}]}},"shapes":[{"ty":"sh","bm":0,"hd":false,"nm":"","d":1,"ks":{"a":1,"k":[{"o":{"x":0,"y":0},"i":{"x":1,"y":1},"s":[{"c":true,"i":[[0,0],[0,0],[0,-14.17],[0,0],[14.17,0],[0,0],[0,14.17],[0,0],[-14.17,0]],"o":[[0,0],[14.17,0],[0,0],[0,14.17],[0,0],[-14.17,0],[0,0],[0,-14.17],[0,0]],"v":[[25.66,0],[446.78,0],[472.44,25.66],[472.44,163.32],[446.78,188.98],[25.66,188.98],[0,163.32],[0,25.66],[25.66,0]]}],"t":0},{"o":{"x":0,"y":0},"i":{"x":1,"y":1},"s":[{"c":true,"i":[[0,0],[0,0],[0,-14.17],[0,0],[14.17,0],[0,0],[0,14.17],[0,0],[-14.17,0]],"o":[[0,0],[14.17,0],[0,0],[0,14.17],[0,0],[-14.17,0],[0,0],[0,-14.17],[0,0]],"v":[[25.66,0],[446.78,0],[472.44,25.66],[472.44,163.32],[446.78,188.98],[25.66,188.98],[0,163.32],[0,25.66],[25.66,0]]}],"t":25.500000324100256},{"o":{"x":0,"y":0},"i":{"x":1,"y":1},"s":[{"c":true,"i":[[0,0],[0,0],[0,-14.17],[0,0],[14.17,0],[0,0],[0,14.17],[0,0],[-14.17,0]],"o":[[0,0],[14.17,0],[0,0],[0,14.17],[0,0],[-14.17,0],[0,0],[0,-14.17],[0,0]],"v":[[25.66,0],[446.78,0],[472.44,25.66],[472.44,163.32],[446.78,188.98],[25.66,188.98],[0,163.32],[0,25.66],[25.66,0]]}],"t":32},{"s":[{"c":true,"i":[[0,0],[0,0],[0,-14.17],[0,0],[14.17,0],[0,0],[0,14.17],[0,0],[-14.17,0]],"o":[[0,0],[14.17,0],[0,0],[0,14.17],[0,0],[-14.17,0],[0,0],[0,-14.17],[0,0]],"v":[[25.66,0],[446.78,0],[472.44,25.66],[472.44,163.32],[446.78,188.98],[25.66,188.98],[0,163.32],[0,25.66],[25.66,0]]}],"t":38.100000489503145}]}},{"ty":"fl","bm":0,"hd":false,"nm":"","c":{"a":1,"k":[{"o":{"x":0,"y":0},"i":{"x":1,"y":1},"s":[0.3216,0.7726,0.3647],"t":0},{"o":{"x":0,"y":0},"i":{"x":1,"y":1},"s":[0.3216,0.7726,0.3647],"t":25.500000324100256},{"o":{"x":0,"y":0},"i":{"x":1,"y":1},"s":[0.3216,0.7726,0.3647],"t":32},{"s":[0.3216,0.7726,0.3647],"t":38.100000489503145}]},"r":1,"o":{"a":1,"k":[{"o":{"x":0,"y":0},"i":{"x":1,"y":1},"s":[100],"t":0},{"o":{"x":0,"y":0},"i":{"x":1,"y":1},"s":[100],"t":25.500000324100256},{"o":{"x":0,"y":0},"i":{"x":1,"y":1},"s":[100],"t":32},{"s":[100],"t":38.100000489503145}]}}],"ind":7},{"ty":4,"nm":"layer1 / g3742 / rect238","sr":1,"st":0,"op":39,"ip":0,"hd":false,"ddd":0,"bm":0,"hasMask":false,"ao":0,"ks":{"a":{"a":1,"k":[{"o":{"x":0,"y":0},"i":{"x":1,"y":1},"s":[236.22,94.49],"t":0},{"o":{"x":0,"y":0},"i":{"x":1,"y":1},"s":[236.22,94.49],"t":6},{"o":{"x":0,"y":0},"i":{"x":1,"y":1},"s":[236.22,94.49],"t":7},{"o":{"x":0,"y":0},"i":{"x":1,"y":1},"s":[236.22,94.49],"t":13},{"o":{"x":0,"y":0},"i":{"x":1,"y":1},"s":[236.22,94.49],"t":19},{"o":{"x":0,"y":0},"i":{"x":1,"y":1},"s":[236.22,94.49],"t":25},{"o":{"x":0,"y":0},"i":{"x":1,"y":1},"s":[236.22,94.49],"t":26},{"o":{"x":0,"y":0},"i":{"x":1,"y":1},"s":[236.22,94.49],"t":32},{"s":[236.22,94.49],"t":38}]},"s":{"a":1,"k":[{"o":{"x":0,"y":0},"i":{"x":1,"y":1},"s":[100,100],"t":0},{"o":{"x":0,"y":0},"i":{"x":1,"y":1},"s":[100,100],"t":6},{"o":{"x":0,"y":0},"i":{"x":1,"y":1},"s":[100,100],"t":7},{"o":{"x":0,"y":0},"i":{"x":1,"y":1},"s":[100,100],"t":13},{"o":{"x":0,"y":0},"i":{"x":1,"y":1},"s":[100,100],"t":19},{"o":{"x":0,"y":0},"i":{"x":1,"y":1},"s":[100,100],"t":25},{"o":{"x":0,"y":0},"i":{"x":1,"y":1},"s":[100,100],"t":26},{"o":{"x":0,"y":0},"i":{"x":1,"y":1},"s":[100,100],"t":32},{"s":[100,100],"t":38}]},"sk":{"a":0,"k":0},"p":{"a":1,"k":[{"o":{"x":0,"y":0},"i":{"x":1,"y":1},"s":[388.75,300],"t":0},{"o":{"x":0,"y":0},"i":{"x":1,"y":1},"s":[388.75,300],"t":6},{"o":{"x":0,"y":0},"i":{"x":1,"y":1},"s":[388.75,300],"t":7},{"o":{"x":0,"y":0},"i":{"x":1,"y":1},"s":[388.75,300],"t":13},{"o":{"x":0,"y":0},"i":{"x":1,"y":1},"s":[388.75,300],"t":19},{"o":{"x":0,"y":0},"i":{"x":1,"y":1},"s":[388.75,300],"t":25},{"o":{"x":0,"y":0},"i":{"x":1,"y":1},"s":[388.75,300],"t":26},{"o":{"x":0,"y":0},"i":{"x":1,"y":1},"s":[388.75,300],"t":32},{"s":[388.75,300],"t":38}]},"r":{"a":1,"k":[{"o":{"x":0,"y":0},"i":{"x":1,"y":1},"s":[0],"t":0},{"o":{"x":0,"y":0},"i":{"x":1,"y":1},"s":[0],"t":6},{"o":{"x":0,"y":0},"i":{"x":1,"y":1},"s":[0],"t":7},{"o":{"x":0,"y":0},"i":{"x":1,"y":1},"s":[0],"t":13},{"o":{"x":0,"y":0},"i":{"x":1,"y":1},"s":[0],"t":19},{"o":{"x":0,"y":0},"i":{"x":1,"y":1},"s":[0],"t":25},{"o":{"x":0,"y":0},"i":{"x":1,"y":1},"s":[0],"t":26},{"o":{"x":0,"y":0},"i":{"x":1,"y":1},"s":[0],"t":32},{"s":[0],"t":38}]},"sa":{"a":0,"k":0},"o":{"a":1,"k":[{"o":{"x":0,"y":0},"i":{"x":1,"y":1},"s":[100],"t":0},{"o":{"x":0,"y":0},"i":{"x":1,"y":1},"s":[100],"t":6},{"o":{"x":0,"y":0},"i":{"x":1,"y":1},"s":[100],"t":7},{"o":{"x":0,"y":0},"i":{"x":1,"y":1},"s":[100],"t":13},{"o":{"x":0,"y":0},"i":{"x":1,"y":1},"s":[100],"t":19},{"o":{"x":0,"y":0},"i":{"x":1,"y":1},"s":[100],"t":25},{"o":{"x":0,"y":0},"i":{"x":1,"y":1},"s":[100],"t":26},{"o":{"x":0,"y":0},"i":{"x":1,"y":1},"s":[100],"t":32},{"s":[100],"t":38}]}},"shapes":[{"ty":"sh","bm":0,"hd":false,"nm":"","d":1,"ks":{"a":1,"k":[{"o":{"x":0,"y":0},"i":{"x":1,"y":1},"s":[{"c":true,"i":[[0,0],[0,0],[0,-14.17],[0,0],[14.17,0],[0,0],[0,14.17],[0,0],[-14.17,0]],"o":[[0,0],[14.17,0],[0,0],[0,14.17],[0,0],[-14.17,0],[0,0],[0,-14.17],[0,0]],"v":[[25.66,0],[446.78,0],[472.44,25.66],[472.44,163.32],[446.78,188.98],[25.66,188.98],[0,163.32],[0,25.66],[25.66,0]]}],"t":0},{"o":{"x":0,"y":0},"i":{"x":1,"y":1},"s":[{"c":true,"i":[[0,0],[0,0],[0,-14.17],[0,0],[14.17,0],[0,0],[0,14.17],[0,0],[-14.17,0]],"o":[[0,0],[14.17,0],[0,0],[0,14.17],[0,0],[-14.17,0],[0,0],[0,-14.17],[0,0]],"v":[[25.66,0],[446.78,0],[472.44,25.66],[472.44,163.32],[446.78,188.98],[25.66,188.98],[0,163.32],[0,25.66],[25.66,0]]}],"t":6},{"o":{"x":0,"y":0},"i":{"x":1,"y":1},"s":[{"c":true,"i":[[0,0],[0,0],[0,-14.17],[0,0],[14.17,0],[0,0],[0,14.17],[0,0],[-14.17,0]],"o":[[0,0],[14.17,0],[0,0],[0,14.17],[0,0],[-14.17,0],[0,0],[0,-14.17],[0,0]],"v":[[25.66,0],[446.78,0],[472.44,25.66],[472.44,163.32],[446.78,188.98],[25.66,188.98],[0,163.32],[0,25.66],[25.66,0]]}],"t":7},{"o":{"x":0,"y":0},"i":{"x":1,"y":1},"s":[{"c":true,"i":[[0,0],[0,0],[0,-14.17],[0,0],[14.17,0],[0,0],[0,14.17],[0,0],[-14.17,0]],"o":[[0,0],[14.17,0],[0,0],[0,14.17],[0,0],[-14.17,0],[0,0],[0,-14.17],[0,0]],"v":[[25.66,0],[446.78,0],[472.44,25.66],[472.44,163.32],[446.78,188.98],[25.66,188.98],[0,163.32],[0,25.66],[25.66,0]]}],"t":13},{"o":{"x":0,"y":0},"i":{"x":1,"y":1},"s":[{"c":true,"i":[[0,0],[0,0],[0,-14.17],[0,0],[14.17,0],[0,0],[0,14.17],[0,0],[-14.17,0]],"o":[[0,0],[14.17,0],[0,0],[0,14.17],[0,0],[-14.17,0],[0,0],[0,-14.17],[0,0]],"v":[[25.66,0],[446.78,0],[472.44,25.66],[472.44,163.32],[446.78,188.98],[25.66,188.98],[0,163.32],[0,25.66],[25.66,0]]}],"t":19},{"o":{"x":0,"y":0},"i":{"x":1,"y":1},"s":[{"c":true,"i":[[0,0],[0,0],[0,-14.17],[0,0],[14.17,0],[0,0],[0,14.17],[0,0],[-14.17,0]],"o":[[0,0],[14.17,0],[0,0],[0,14.17],[0,0],[-14.17,0],[0,0],[0,-14.17],[0,0]],"v":[[25.66,0],[446.78,0],[472.44,25.66],[472.44,163.32],[446.78,188.98],[25.66,188.98],[0,163.32],[0,25.66],[25.66,0]]}],"t":25},{"o":{"x":0,"y":0},"i":{"x":1,"y":1},"s":[{"c":true,"i":[[0,0],[0,0],[0,-14.17],[0,0],[14.17,0],[0,0],[0,14.17],[0,0],[-14.17,0]],"o":[[0,0],[14.17,0],[0,0],[0,14.17],[0,0],[-14.17,0],[0,0],[0,-14.17],[0,0]],"v":[[25.66,0],[446.78,0],[472.44,25.66],[472.44,163.32],[446.78,188.98],[25.66,188.98],[0,163.32],[0,25.66],[25.66,0]]}],"t":26},{"o":{"x":0,"y":0},"i":{"x":1,"y":1},"s":[{"c":true,"i":[[0,0],[0,0],[0,-14.17],[0,0],[14.17,0],[0,0],[0,14.17],[0,0],[-14.17,0]],"o":[[0,0],[14.17,0],[0,0],[0,14.17],[0,0],[-14.17,0],[0,0],[0,-14.17],[0,0]],"v":[[25.66,0],[446.78,0],[472.44,25.66],[472.44,163.32],[446.78,188.98],[25.66,188.98],[0,163.32],[0,25.66],[25.66,0]]}],"t":32},{"s":[{"c":true,"i":[[0,0],[0,0],[0,-14.17],[0,0],[14.17,0],[0,0],[0,14.17],[0,0],[-14.17,0]],"o":[[0,0],[14.17,0],[0,0],[0,14.17],[0,0],[-14.17,0],[0,0],[0,-14.17],[0,0]],"v":[[25.66,0],[446.78,0],[472.44,25.66],[472.44,163.32],[446.78,188.98],[25.66,188.98],[0,163.32],[0,25.66],[25.66,0]]}],"t":38}]}},{"ty":"fl","bm":0,"hd":false,"nm":"","c":{"a":1,"k":[{"o":{"x":0,"y":0},"i":{"x":1,"y":1},"s":[0.6,0.6,0.6],"t":0},{"o":{"x":0,"y":0},"i":{"x":1,"y":1},"s":[0.6,0.6,0.6],"t":6},{"o":{"x":0,"y":0},"i":{"x":1,"y":1},"s":[0.6,0.6,0.6],"t":7},{"o":{"x":0,"y":0},"i":{"x":1,"y":1},"s":[0.6,0.6,0.6],"t":13},{"o":{"x":0,"y":0},"i":{"x":1,"y":1},"s":[0.6,0.6,0.6],"t":19},{"o":{"x":0,"y":0},"i":{"x":1,"y":1},"s":[0.6,0.6,0.6],"t":25},{"o":{"x":0,"y":0},"i":{"x":1,"y":1},"s":[0.6,0.6,0.6],"t":26},{"o":{"x":0,"y":0},"i":{"x":1,"y":1},"s":[0.6,0.6,0.6],"t":32},{"s":[0.6,0.6,0.6],"t":38}]},"r":1,"o":{"a":1,"k":[{"o":{"x":0,"y":0},"i":{"x":1,"y":1},"s":[100],"t":0},{"o":{"x":0,"y":0},"i":{"x":1,"y":1},"s":[100],"t":6},{"o":{"x":0,"y":0},"i":{"x":1,"y":1},"s":[100],"t":7},{"o":{"x":0,"y":0},"i":{"x":1,"y":1},"s":[100],"t":13},{"o":{"x":0,"y":0},"i":{"x":1,"y":1},"s":[100],"t":19},{"o":{"x":0,"y":0},"i":{"x":1,"y":1},"s":[100],"t":25},{"o":{"x":0,"y":0},"i":{"x":1,"y":1},"s":[100],"t":26},{"o":{"x":0,"y":0},"i":{"x":1,"y":1},"s":[100],"t":32},{"s":[100],"t":38}]}}],"ind":8}],"v":"5.7.0","fr":30,"op":38.100000489503145,"ip":0,"assets":[]}